{
  "@context": "https://schema.org",
  "generated_at": "2026-07-11T18:00:11.687Z",
  "base_url": "https://example.com",
  "currency": "ILS",
  "count": 16,
  "products": [
    {
      "id": "3b768411-8d69-47fa-a987-3d43374dd154",
      "slug": "mksykv-chvts-1srwh8",
      "name": "מקסיקו חוץ ",
      "name_translations": {},
      "description": "",
      "short_description": null,
      "sku": null,
      "brand": "אדידס",
      "price": 99.9,
      "base_price": 139.9,
      "sale_price": 99.9,
      "currency": "ILS",
      "images": [
        "https://example.com/assets/product-1783724268633-m48io.webp"
      ],
      "in_stock": true,
      "stock_status": "in_stock",
      "url": "https://example.com/product/mksykv-chvts-1srwh8",
      "categories": [],
      "updated_at": "2026-07-10T22:58:07.293Z"
    },
    {
      "id": "77f16775-0529-4507-ab7c-839e19dab72e",
      "slug": "mksykv-byt-12spci",
      "name": "מקסיקו בית",
      "name_translations": {},
      "description": "",
      "short_description": null,
      "sku": null,
      "brand": "אדידס",
      "price": 99.9,
      "base_price": 139.9,
      "sale_price": 99.9,
      "currency": "ILS",
      "images": [
        "https://example.com/assets/product-1783724218513-n9zm4a.webp"
      ],
      "in_stock": true,
      "stock_status": "in_stock",
      "url": "https://example.com/product/mksykv-byt-12spci",
      "categories": [],
      "updated_at": "2026-07-10T22:57:18.137Z"
    },
    {
      "id": "2e2d5682-60fb-4ba8-a9c8-96392d867faa",
      "slug": "ypn-byt-slwro5",
      "name": "יפן בית",
      "name_translations": {},
      "description": "",
      "short_description": null,
      "sku": null,
      "brand": "אדידס",
      "price": 99.9,
      "base_price": 139.9,
      "sale_price": 99.9,
      "currency": "ILS",
      "images": [
        "https://example.com/assets/product-1783724144514-rueqaj.webp"
      ],
      "in_stock": true,
      "stock_status": "in_stock",
      "url": "https://example.com/product/ypn-byt-slwro5",
      "categories": [],
      "updated_at": "2026-07-10T22:56:39.542Z"
    },
    {
      "id": "1cb84dc1-81b5-4cf6-970c-820ec92650b7",
      "slug": "grmnyh-byt-ltnc7f",
      "name": "גרמניה בית",
      "name_translations": {},
      "description": "",
      "short_description": null,
      "sku": null,
      "brand": "אדידס",
      "price": 99.9,
      "base_price": 139.9,
      "sale_price": 99.9,
      "currency": "ILS",
      "images": [
        "https://example.com/assets/product-1783724083867-ihlo9.webp"
      ],
      "in_stock": true,
      "stock_status": "in_stock",
      "url": "https://example.com/product/grmnyh-byt-ltnc7f",
      "categories": [],
      "updated_at": "2026-07-10T22:55:22.520Z"
    },
    {
      "id": "fc7c1fdd-0e78-4a18-bec8-bd57e565edb3",
      "slug": "pvrtvgl-byt-b426zw",
      "name": "פורטוגל בית ",
      "name_translations": {},
      "description": "",
      "short_description": null,
      "sku": null,
      "brand": "פומה",
      "price": 99.9,
      "base_price": 139.9,
      "sale_price": 99.9,
      "currency": "ILS",
      "images": [
        "https://example.com/assets/product-1783724024311-ya4w1.webp"
      ],
      "in_stock": true,
      "stock_status": "in_stock",
      "url": "https://example.com/product/pvrtvgl-byt-b426zw",
      "categories": [],
      "updated_at": "2026-07-11T09:55:26.447Z"
    },
    {
      "id": "6efe0ca0-4851-4c42-ab7b-a9dadc0a3430",
      "slug": "brzyl-chvts-goawub",
      "name": "ברזיל חוץ",
      "name_translations": {},
      "description": "",
      "short_description": null,
      "sku": null,
      "brand": "גורדן",
      "price": 99.9,
      "base_price": 139.9,
      "sale_price": 99.9,
      "currency": "ILS",
      "images": [
        "https://example.com/assets/product-1783723973177-76ij8.webp"
      ],
      "in_stock": true,
      "stock_status": "in_stock",
      "url": "https://example.com/product/brzyl-chvts-goawub",
      "categories": [],
      "updated_at": "2026-07-10T22:53:32.936Z"
    },
    {
      "id": "7801a95b-0006-4d05-89d3-b0fb3313f8c7",
      "slug": "sprd-chvts-b8njv0",
      "name": "ספרד חוץ ",
      "name_translations": {},
      "description": "",
      "short_description": null,
      "sku": null,
      "brand": "אדידס",
      "price": 99.9,
      "base_price": 139.9,
      "sale_price": 99.9,
      "currency": "ILS",
      "images": [
        "https://example.com/assets/product-1783723916409-2plph4.webp"
      ],
      "in_stock": true,
      "stock_status": "in_stock",
      "url": "https://example.com/product/sprd-chvts-b8njv0",
      "categories": [],
      "updated_at": "2026-07-10T22:52:37.518Z"
    },
    {
      "id": "4aea98b9-fa35-411f-aad1-318e35a1d468",
      "slug": "pvrtvgl-chvts-3xovs3",
      "name": "פורטוגל חוץ",
      "name_translations": {},
      "description": "",
      "short_description": null,
      "sku": null,
      "brand": "פומה",
      "price": 99.9,
      "base_price": 139.9,
      "sale_price": 99.9,
      "currency": "ILS",
      "images": [
        "https://example.com/assets/product-1783723843018-jinjsh.webp"
      ],
      "in_stock": true,
      "stock_status": "in_stock",
      "url": "https://example.com/product/pvrtvgl-chvts-3xovs3",
      "categories": [],
      "updated_at": "2026-07-10T22:51:28.331Z"
    },
    {
      "id": "cb501088-b68a-4fbd-9db8-145d37974c35",
      "slug": "anglyh-byt-ycqypj",
      "name": "אנגליה בית",
      "name_translations": {},
      "description": "",
      "short_description": null,
      "sku": null,
      "brand": "נייק",
      "price": 99.9,
      "base_price": 139.9,
      "sale_price": 99.9,
      "currency": "ILS",
      "images": [
        "https://example.com/assets/product-1783723810111-3x6btr.webp"
      ],
      "in_stock": true,
      "stock_status": "in_stock",
      "url": "https://example.com/product/anglyh-byt-ycqypj",
      "categories": [],
      "updated_at": "2026-07-10T22:50:28.050Z"
    },
    {
      "id": "04fbf3fc-474f-41c3-9f02-6601de6d86d1",
      "slug": "hvlnd-byt-dwv09d",
      "name": "הולנד בית",
      "name_translations": {},
      "description": "",
      "short_description": null,
      "sku": null,
      "brand": "נייק",
      "price": 99.9,
      "base_price": 139.9,
      "sale_price": 99.9,
      "currency": "ILS",
      "images": [
        "https://example.com/assets/product-1783723771026-u0zkwc.webp"
      ],
      "in_stock": true,
      "stock_status": "in_stock",
      "url": "https://example.com/product/hvlnd-byt-dwv09d",
      "categories": [],
      "updated_at": "2026-07-10T22:49:53.214Z"
    },
    {
      "id": "d3ec8f67-1cad-492c-93a9-4d12df40526e",
      "slug": "tsrpt-byt-80zsf2",
      "name": "צרפת בית",
      "name_translations": {},
      "description": "",
      "short_description": null,
      "sku": null,
      "brand": "נייק",
      "price": 99.9,
      "base_price": 139.9,
      "sale_price": 99.9,
      "currency": "ILS",
      "images": [
        "https://example.com/assets/product-1783723722280-ydb7fmh.webp"
      ],
      "in_stock": true,
      "stock_status": "in_stock",
      "url": "https://example.com/product/tsrpt-byt-80zsf2",
      "categories": [],
      "updated_at": "2026-07-10T22:49:10.913Z"
    },
    {
      "id": "15104817-b5a0-4923-bfbd-a9da4aeb86de",
      "slug": "sprd-byt-y4wdnl",
      "name": "ספרד בית",
      "name_translations": {},
      "description": "",
      "short_description": null,
      "sku": null,
      "brand": "אדידס",
      "price": 99.9,
      "base_price": 139.9,
      "sale_price": 99.9,
      "currency": "ILS",
      "images": [
        "https://example.com/assets/product-1783723396258-eu824j.webp"
      ],
      "in_stock": true,
      "stock_status": "in_stock",
      "url": "https://example.com/product/sprd-byt-y4wdnl",
      "categories": [],
      "updated_at": "2026-07-10T22:44:14.044Z"
    },
    {
      "id": "1b7d1203-9b6f-4f6c-88bb-464aa15d03ce",
      "slug": "argntynh-chvts-dapc2f",
      "name": "ארגנטינה חוץ",
      "name_translations": {},
      "description": "",
      "short_description": null,
      "sku": null,
      "brand": "אדידס",
      "price": 99.9,
      "base_price": 139.9,
      "sale_price": 99.9,
      "currency": "ILS",
      "images": [
        "https://example.com/assets/product-1783723350703-gu5lx8.webp"
      ],
      "in_stock": true,
      "stock_status": "in_stock",
      "url": "https://example.com/product/argntynh-chvts-dapc2f",
      "categories": [],
      "updated_at": "2026-07-10T22:42:57.200Z"
    },
    {
      "id": "567689b1-8186-4b75-a56f-911f802da578",
      "slug": "tsrpt-chvts-0cduwo",
      "name": "צרפת חוץ",
      "name_translations": {},
      "description": "",
      "short_description": null,
      "sku": null,
      "brand": "נייק",
      "price": 99.9,
      "base_price": 139.9,
      "sale_price": 99.9,
      "currency": "ILS",
      "images": [
        "https://example.com/assets/product-1783723271677-nfd9zco.webp"
      ],
      "in_stock": true,
      "stock_status": "in_stock",
      "url": "https://example.com/product/tsrpt-chvts-0cduwo",
      "categories": [],
      "updated_at": "2026-07-10T22:41:53.973Z"
    },
    {
      "id": "e7e731ff-443a-4f33-a2d2-3261cd83b610",
      "slug": "anglyh-chvts-1ncunn",
      "name": "אנגליה חוץ",
      "name_translations": {},
      "description": "",
      "short_description": null,
      "sku": null,
      "brand": "נייק",
      "price": 99.9,
      "base_price": 139.9,
      "sale_price": 99.9,
      "currency": "ILS",
      "images": [
        "https://example.com/assets/product-1783723198875-g3wam9.webp"
      ],
      "in_stock": true,
      "stock_status": "in_stock",
      "url": "https://example.com/product/anglyh-chvts-1ncunn",
      "categories": [],
      "updated_at": "2026-07-10T22:40:38.972Z"
    },
    {
      "id": "33006e9a-78a8-41a2-97e5-7339432e52b6",
      "slug": "argntynh-byt-ml4ba0",
      "name": "ארגנטינה בית",
      "name_translations": {},
      "description": "",
      "short_description": null,
      "sku": null,
      "brand": "אדידס",
      "price": 99.9,
      "base_price": 139.9,
      "sale_price": 99.9,
      "currency": "ILS",
      "images": [
        "https://example.com/assets/product-1783722712101-u5pz7a.webp",
        "https://example.com/assets/product-1783722719661-e9su76.webp"
      ],
      "in_stock": true,
      "stock_status": "in_stock",
      "url": "https://example.com/product/argntynh-byt-ml4ba0",
      "categories": [],
      "updated_at": "2026-07-10T22:39:36.513Z"
    }
  ]
}